regexable/__init__.py
regexable/core.py
regexable-0.1.1.dist-info/LICENSE
regexable-0.1.1.dist-info/METADATA
regexable-0.1.1.dist-info/WHEEL
regexable-0.1.1.dist-info/top_level.txt
regexable-0.1.1.dist-info/RECORD
