Metadata-Version: 2.1
Name: regexable
Version: 0.1.1
Summary: A more readable alternative to regular expressions.
Home-page: https://github.com/Orion-F/regexable
Author: Orion Forowycz
Classifier: Programming Language :: Python :: 3
Classifier: License :: OSI Approved :: MIT License
Classifier: Operating System :: OS Independent
Requires-Python: >=3.6
License-File: LICENSE
